scmorph/__init__.py
scmorph/_version.py
scmorph/datasets/__init__.py
scmorph/datasets/_datasets.py
scmorph/io/__init__.py
scmorph/io/io.py
scmorph/logging/__init__.py
scmorph/logging/logging.py
scmorph/pl/__init__.py
scmorph/pl/dr.py
scmorph/pp/__init__.py
scmorph/pp/aggregate.py
scmorph/pp/batch_effects.py
scmorph/pp/correlation.py
scmorph/pp/feature_selection.py
scmorph/pp/processing.py
scmorph/qc/__init__.py
scmorph/qc/images.py
scmorph/qc/outliers.py
scmorph/tl/__init__.py
scmorph/tl/hit_calling.py
scmorph/tl/trajectories.py
scmorph/utils/__init__.py
scmorph/utils/r_functions.py
scmorph/utils/utils.py
scmorph-0.4.0.dist-info/METADATA
scmorph-0.4.0.dist-info/WHEEL
scmorph-0.4.0.dist-info/licenses/LICENSE
scmorph-0.4.0.dist-info/RECORD
