Metadata-Version: 2.4
Name: scmorph
Version: 0.4.0
Summary: Single-cell morphological analysis
Project-URL: Documentation, https://scmorph.readthedocs.io/
Project-URL: Homepage, https://github.com/edbiomedai/scmorph
Project-URL: Source, https://github.com/edbiomedai/scmorph
Author: Jesko Wagner
Maintainer-email: Jesko Wagner <35219306+jeskowagner@users.noreply.github.com>
License: MIT License
License-File: LICENSE
Classifier: Programming Language :: Python :: 3 :: Only
Classifier: Programming Language :: Python :: 3.10
Classifier: Programming Language :: Python :: 3.11
Classifier: Programming Language :: Python :: 3.12
Classifier: Programming Language :: Python :: 3.13
Requires-Python: >=3.10
Requires-Dist: anndata>=0.8
Requires-Dist: certifi
Requires-Dist: formulaic
Requires-Dist: matplotlib>=3.6
Requires-Dist: numba>=0.56
Requires-Dist: numpy>=1.23
Requires-Dist: pandas>=2.2
Requires-Dist: patsy
Requires-Dist: pyarrow
Requires-Dist: pyod
Requires-Dist: scanpy
Requires-Dist: scikit-learn>=1.1
Requires-Dist: seaborn
Requires-Dist: session-info
Requires-Dist: tqdm
Provides-Extra: dev
Requires-Dist: pre-commit; extra == 'dev'
Requires-Dist: setuptools-scm; extra == 'dev'
Requires-Dist: twine>=4.0.2; extra == 'dev'
Provides-Extra: doc
Requires-Dist: docutils!=0.18.*,!=0.19.*,>=0.8; extra == 'doc'
Requires-Dist: ipykernel; extra == 'doc'
Requires-Dist: ipython; extra == 'doc'
Requires-Dist: myst-nb>=1.1; extra == 'doc'
Requires-Dist: pandas; extra == 'doc'
Requires-Dist: scanpydoc>=0.14.1; extra == 'doc'
Requires-Dist: sphinx-autodoc-typehints; extra == 'doc'
Requires-Dist: sphinx-book-theme>=1; extra == 'doc'
Requires-Dist: sphinx-copybutton; extra == 'doc'
Requires-Dist: sphinx-tabs; extra == 'doc'
Requires-Dist: sphinx>=4; extra == 'doc'
Requires-Dist: sphinxcontrib-bibtex>=1; extra == 'doc'
Requires-Dist: sphinxext-opengraph; extra == 'doc'
Provides-Extra: test
Requires-Dist: coverage; extra == 'test'
Requires-Dist: pytest; extra == 'test'
Requires-Dist: pytest-cov; extra == 'test'
Requires-Dist: pytest-nunit; extra == 'test'
